weex_client/__init__.py
weex_client/__version__.py
weex_client/auth.py
weex_client/client.py
weex_client/config.py
weex_client/exceptions.py
weex_client/models.py
weex_client/sync.py
weex_client/types.py
weex_client/utils.py
weex_client/websocket.py
weex_client-0.2.3.dist-info/METADATA
weex_client-0.2.3.dist-info/WHEEL
weex_client-0.2.3.dist-info/licenses/LICENSE
weex_client-0.2.3.dist-info/RECORD
