Metadata-Version: 2.4
Name: weex-client
Version: 0.2.3
Summary: Modern async-first Weex API client for Python 3.14+
Project-URL: Homepage, https://github.com/xsa-dev
Project-URL: Repository, https://github.com/xsa-dev/weex-client.git
Project-URL: Bug Tracker, https://github.com/xsa-dev/weex-client/issues
Author-email: xsa-dev <saleksey67@gmail.com>
License: MIT License
License-File: LICENSE
Keywords: api,async,client,crypto,trading,weex
Classifier: Development Status :: 4 - Beta
Classifier: Intended Audience :: Developers
Classifier: License :: OSI Approved :: MIT License
Classifier: Operating System :: OS Independent
Classifier: Programming Language :: Python :: 3
Classifier: Programming Language :: Python :: 3.11
Classifier: Programming Language :: Python :: 3.12
Classifier: Programming Language :: Python :: 3.13
Classifier: Programming Language :: Python :: 3.14
Classifier: Programming Language :: Python :: 3.15
Classifier: Topic :: Office/Business :: Financial :: Investment
Classifier: Topic :: Software Development :: Libraries :: Python Modules
Classifier: Typing :: Typed
Requires-Python: >=3.11
Requires-Dist: httpx>=0.27.0
Requires-Dist: packaging>=24.0
Requires-Dist: pydantic-settings>=2.5.0
Requires-Dist: pydantic>=2.8.0
Requires-Dist: structlog>=24.0.0
Requires-Dist: tenacity>=9.0.0
Requires-Dist: websockets>=15.0
Provides-Extra: dev
Requires-Dist: black>=24.0.0; extra == 'dev'
Requires-Dist: coverage>=7.0.0; extra == 'dev'
Requires-Dist: mypy>=1.12.0; extra == 'dev'
Requires-Dist: pre-commit>=3.8.0; extra == 'dev'
Requires-Dist: pytest-asyncio>=0.24.0; extra == 'dev'
Requires-Dist: pytest-mock>=3.14.0; extra == 'dev'
Requires-Dist: pytest>=8.0.0; extra == 'dev'
Requires-Dist: ruff>=0.6.0; extra == 'dev'
Provides-Extra: docs
Requires-Dist: myst-parser>=4.0.0; extra == 'docs'
Requires-Dist: sphinx-autodoc-typehints>=2.0.0; extra == 'docs'
Requires-Dist: sphinx-rtd-theme>=2.0.0; extra == 'docs'
Requires-Dist: sphinx>=8.0.0; extra == 'docs'
